tsmart/__init__.py
tsmart/tsmart.py
tsmart-0.1.0.dist-info/LICENSE
tsmart-0.1.0.dist-info/METADATA
tsmart-0.1.0.dist-info/WHEEL
tsmart-0.1.0.dist-info/top_level.txt
tsmart-0.1.0.dist-info/RECORD
