Metadata-Version: 2.1
Name: tsmart
Version: 0.1.0
Summary: Library for accessing T-Smart thermostats
Author-email: Paul Warren <pdw@ex-parrot.com>
Project-URL: Homepage, https://github.com/pdw-mb/tsmart
Project-URL: Bug Tracker, https://github.com/pdw-mb/tsmart/issues
Classifier: Programming Language :: Python :: 3
Classifier: License :: OSI Approved :: MIT License
Classifier: Operating System :: OS Independent
Requires-Python: >=3.7
License-File: LICENSE
Requires-Dist: asyncio-dgram
